cronctrl/__init__.py
cronctrl/cli.py
cronctrl/config.py
cronctrl/cron.py
cronctrl/logrotate.py
cronctrl/logs.py
cronctrl/runner.py
cronctrl/status.py
cronctrl/util.py
cronctrl-0.2.2.dist-info/METADATA
cronctrl-0.2.2.dist-info/WHEEL
cronctrl-0.2.2.dist-info/entry_points.txt
cronctrl-0.2.2.dist-info/top_level.txt
cronctrl-0.2.2.dist-info/RECORD
