Metadata-Version: 2.4
Name: cronctrl
Version: 0.2.2
Summary: Lightweight cron orchestration tool
Requires-Python: >=3.11
Requires-Dist: PyYAML>=6.0
Provides-Extra: dev
Requires-Dist: pytest>=7.0; extra == "dev"
